chromium_auto_installer/__init__.py
chromium_auto_installer-1.0.1.dist-info/LICENSE
chromium_auto_installer-1.0.1.dist-info/METADATA
chromium_auto_installer-1.0.1.dist-info/WHEEL
chromium_auto_installer-1.0.1.dist-info/top_level.txt
chromium_auto_installer-1.0.1.dist-info/zip-safe
chromium_auto_installer-1.0.1.dist-info/RECORD
